parsy_extn/__init__.py
parsy_extn-0.0.2.dist-info/LICENCE.md
parsy_extn-0.0.2.dist-info/METADATA
parsy_extn-0.0.2.dist-info/WHEEL
parsy_extn-0.0.2.dist-info/top_level.txt
parsy_extn-0.0.2.dist-info/RECORD
