Metadata-Version: 2.1
Name: parsy-extn
Version: 0.0.2
Summary: Some small extensions to parsy
Home-page: http://github.com/jan-g/{name}
Author: jan grant 
Author-email: parsy-extn@ioctl.org
License: UNKNOWN
Platform: UNKNOWN
Classifier: Development Status :: 4 - Beta
Classifier: Intended Audience :: Developers
Classifier: License :: OSI Approved :: Apache Software License
Classifier: Topic :: Software Development :: Compilers
Classifier: Topic :: Software Development :: Interpreters
Classifier: Topic :: Text Processing
Requires-Dist: parsy
